term_music/__init__.py
term_music/app.py
term_music/app_data.py
term_music/commands.py
term_music/config.py
term_music/keyboard.py
term_music/main.py
term_music/player.py
term_music/ui.py
term_music/domain/__init__.py
term_music/domain/music_library.py
term_music/domain/playlist.py
term_music/domain/song.py
term_music-0.2.1.dist-info/LICENCE.txt
term_music-0.2.1.dist-info/METADATA
term_music-0.2.1.dist-info/WHEEL
term_music-0.2.1.dist-info/entry_points.txt
term_music-0.2.1.dist-info/top_level.txt
term_music-0.2.1.dist-info/RECORD
