Metadata-Version: 2.1
Name: term-music
Version: 0.2.1
Summary: A music player for the terminal
Author: tracksuitdev
Project-URL: Homepage, https://github.com/tracksuitdev/term-music
Project-URL: Source, https://github.com/tracksuitdev/term-music
Keywords: terminal,music,player,library,youtube-dl
Requires-Python: >=3.7.0
License-File: LICENCE.txt
Requires-Dist: numpy
Requires-Dist: pygame
Requires-Dist: pydub
Requires-Dist: blessed
